setup.py
app/__init__.py
app/database.py
app/account/__init__.py
app/account/models.py
app/account/views.py
app/blog/__init__.py
app/blog/models.py
app/blog/views.py
app/core/__init__.py
app/core/models.py
app/core/views.py
pyboxio.egg-info/PKG-INFO
pyboxio.egg-info/SOURCES.txt
pyboxio.egg-info/dependency_links.txt
pyboxio.egg-info/top_level.txt