Metadata-Version: 1.1
Name: pyboxio
Version: 0.0.1
Summary: Pybox is a modular CMS with easy click-plugin support.
Home-page: https://github.com/PaluMacil/pybox
Author: Dan Wolf
Author-email: dcwolf@gmail.com
License: GPLv2
Keywords: blog,cms,document management,content management
Platform: OS Independent
Classifier: Development Status :: 2 - Pre-Alpha
Classifier: Topic :: Utilities
Classifier: License :: OSI Approved :: GNU General Public License v2 (GPLv2)
